stxmalign/__init__.py
stxmalign/myRoll.py
stxmalign/stxmalign.py
stxmalign-0.0.10.data/data/my_data/data_file
stxmalign-0.0.10.dist-info/DESCRIPTION.rst
stxmalign-0.0.10.dist-info/METADATA
stxmalign-0.0.10.dist-info/RECORD
stxmalign-0.0.10.dist-info/WHEEL
stxmalign-0.0.10.dist-info/entry_points.txt
stxmalign-0.0.10.dist-info/metadata.json
stxmalign-0.0.10.dist-info/top_level.txt
