Metadata-Version: 2.0
Name: stxmalign
Version: 0.0.10
Summary: Pixel Alignment of STXM images.
Home-page: http://carlos.reis@gitlab.elettra.eu/carlos.reis/stxmalign
Author: Elettra SciComp
Author-email: carlos.reis@elettra.eu
License: MIT
Keywords: stxm images alignment
Platform: UNKNOWN
Classifier: Development Status :: 3 - Alpha
Classifier: Intended Audience :: Developers
Classifier: Topic :: Software Development :: Build Tools
Classifier: License :: OSI Approved :: MIT License
Classifier: Programming Language :: Python :: 2
Classifier: Programming Language :: Python :: 2.7
Classifier: Programming Language :: Python :: 3
Classifier: Programming Language :: Python :: 3.3
Classifier: Programming Language :: Python :: 3.4
Classifier: Programming Language :: Python :: 3.5
Requires-Dist: h5py
Requires-Dist: matplotlib
Requires-Dist: numpy
Requires-Dist: pyqtgraph
Requires-Dist: tifffile
Provides-Extra: dev
Requires-Dist: check-manifest; extra == 'dev'
Provides-Extra: test
Requires-Dist: coverage; extra == 'test'
